{
  "programName": "rs2client.exe",
  "functionName": "FUN_1400fbf80",
  "functionEntryPoint": "1400fbf80",
  "targetAddress": "1400fbf80",
  "packetName": "IF_OPENSUB_ACTIVE_LOC",
  "bufferParam": "param_2",
  "legacyShape": [],
  "status": "ok",
  "fieldCount": 10,
  "statements": [
    "undefined * FUN_1400fbf80(longlong *param_1,longlong param_2,undefined8 param_3,uint param_4)\r\n\r\n{\r\n  int *piVar1;",
    "longlong *plVar2;",
    "byte bVar3;",
    "byte bVar4;",
    "byte bVar5;",
    "byte bVar6;",
    "char cVar7;",
    "longlong lVar8;",
    "longlong lVar9;",
    "byte bVar10;",
    "byte bVar11;",
    "undefined *puVar12;",
    "longlong *plVar13;",
    "uint uVar14;",
    "uint uVar15;",
    "longlong *plVar16;",
    "longlong lVar17;",
    "int iVar18;",
    "uint uVar19;",
    "uint uVar20;",
    "undefined2 uStack_146;",
    "uint uStack_144;",
    "undefined4 uVar21;",
    "uint uStack_13c;",
    "undefined8 uStack_134;",
    "undefined4 uStack_12c;",
    "undefined4 uStack_128;",
    "undefined4 local_124;",
    "undefined4 uStack_120;",
    "undefined4 uStack_11c;",
    "undefined4 uStack_118;",
    "longlong *local_110;",
    "longlong *local_108;",
    "undefined **local_f8;",
    "uint local_f0;",
    "uint uStack_ec;",
    "uint local_e8;",
    "ulonglong local_e4;",
    "undefined8 uStack_dc;",
    "undefined4 local_d4;",
    "undefined4 uStack_d0;",
    "undefined4 uStack_cc;",
    "undefined4 uStack_c8;",
    "undefined8 local_c4;",
    "undefined8 uStack_bc;",
    "undefined4 local_b4;",
    "uint local_ac;",
    "longlong *local_a8;",
    "undefined8 uStack_a0;",
    "undefined4 local_98;",
    "undefined4 local_94;",
    "undefined8 local_90;",
    "undefined4 local_88;",
    "undefined8 local_80;",
    "undefined1 local_78;",
    "undefined8 local_68;",
    "undefined8 uStack_60;",
    "undefined8 local_58;",
    "undefined8 uStack_50;",
    "undefined8 local_48;",
    "undefined8 uStack_40;",
    "lVar8 = *(longlong *)(param_2 + 0x18);",
    "lVar17 = lVar8 + 4;",
    "plVar16 = (longlong *)0x0;",
    "*(longlong *)(param_2 + 0x18) = lVar17;",
    "lVar9 = *(longlong *)(param_2 + 0x10);",
    "bVar3 = *(byte *)(lVar9 + -1 + lVar17);",
    "bVar4 = *(byte *)(lVar9 + -2 + lVar17);",
    "bVar5 = *(byte *)(lVar9 + -3 + lVar17);",
    "bVar6 = *(byte *)(lVar9 + -4 + lVar17);",
    "*(longlong *)(param_2 + 0x18) = lVar8 + 5;",
    "cVar7 = *(char *)(lVar9 + lVar17);",
    "lVar17 = lVar8 + 0xd;",
    "*(longlong *)(param_2 + 0x18) = lVar17;",
    "uVar14 = (((uint)*(byte *)(lVar9 + -2 + lVar17) * 0x100 + (uint)*(byte *)(lVar9 + -1 + lVar17)) *\r\n            0x100 + (uint)*(byte *)(lVar9 + -4 + lVar17)) * 0x100 +\r\n           (uint)*(byte *)(lVar9 + -3 + lVar17);",
    "uVar15 = 0xffffffff;",
    "uVar19 = 0;",
    "if (uVar14 == 0xffffffff) {\r\n    uVar20 = 0;",
    "}\r\n  else {\r\n    uVar19 = uVar14 & 0x3fff;",
    "uVar20 = uVar14 >> 0xe & 0x3fff;",
    "uVar15 = uVar14 >> 0x1c & 3;",
    "}\r\n  *(longlong *)(param_2 + 0x18) = lVar8 + 0xe;",
    "bVar10 = *(char *)(lVar9 + lVar17) + 0x80;",
    "*(longlong *)(param_2 + 0x18) = lVar8 + 0x12;",
    "uVar14 = *(uint *)(lVar9 + lVar8 + 0xe);",
    "uVar14 = (uVar14 >> 8 ^ uVar14 << 8) & 0xff00ff ^ uVar14 << 8;",
    "lVar17 = lVar8 + 0x1c;",
    "*(longlong *)(param_2 + 0x18) = lVar17;",
    "iVar18 = (uint)(byte)(*(char *)(lVar9 + -2 + lVar17) + 0x80) +\r\n           (uint)*(byte *)(lVar9 + -1 + lVar17) * 0x100;",
    "*(longlong *)(param_2 + 0x18) = lVar8 + 0x20;",
    "bVar11 = bVar10 >> 2 & 0x1f;",
    "uStack_144 = 0;",
    "uStack_13c = 0;",
    "uStack_134 = 0;",
    "uStack_12c = 0;",
    "uStack_128 = 0;",
    "local_124 = 0x3f800000;",
    "uStack_120 = 0x3f800000;",
    "uStack_11c = 0x3f800000;",
    "uStack_118 = 0;",
    "uVar21 = 0;",
    "local_d4 = 0x3f800000;",
    "if ((char)-((char)bVar10 >> 7) != '\\0') {\r\n    local_68 = 0;",
    "uStack_60 = 0x3f80000000000000;",
    "local_48 = 0;",
    "uStack_40 = 0;",
    "local_58 = 0;",
    "uStack_50 = 0;",
    "FUN_14010e3d0(&local_68,0,-((char)bVar10 >> 7),lVar9,bVar11,0,0x3f800000);",
    "uStack_12c = (undefined4)uStack_50;",
    "uStack_128 = uStack_50._4_4_;",
    "local_124 = (undefined4)local_48;",
    "uStack_120 = (undefined4)((ulonglong)local_48 >> 0x20);",
    "uStack_11c = (undefined4)uStack_40;",
    "uStack_118 = (undefined4)((ulonglong)uStack_40 >> 0x20);",
    "uStack_144 = (uint)local_68 ^ 0x80000000;",
    "uStack_13c = (uint)uStack_60 ^ 0x80000000;",
    "param_4 = local_58._4_4_ ^ 0x80000000;",
    "uStack_134 = local_58 ^ 0x8000000000000000;",
    "uVar21 = local_68._4_4_;",
    "local_d4 = uStack_60._4_4_;",
    "}\r\n  if (*(longlong *)(*(longlong *)(*param_1 + 0x198c0) + 0x108) == 0) {\r\n    puVar12 = &DAT_140c9c270;",
    "}\r\n  else {\r\n    lVar17 = FUN_1403370e0(*(longlong *)(*param_1 + 0x198c0) + 0x30,iVar18,0,param_4,bVar11,uVar21,\r\n                           local_d4);",
    "if (*(longlong *)(lVar17 + 8) == 0) {\r\n      puVar12 = &DAT_140c9bb40;",
    "}\r\n    else {\r\n      local_e4 = CONCAT44(uStack_144,CONCAT22(uStack_146,CONCAT11(bVar10,bVar11))) &\r\n                 0xffffffffffff03ff;",
    "uStack_dc = CONCAT44(uStack_13c,uVar21);",
    "lVar17 = *(longlong *)(*param_1 + 0x19888);",
    "local_f8 = &PTR_FUN_140b8e038;",
    "local_c4 = CONCAT44(local_124,uStack_128);",
    "uStack_bc = CONCAT44(uStack_11c,uStack_120);",
    "piVar1 = (int *)(lVar17 + 0x10);",
    "*piVar1 = *piVar1 + 1;",
    "*(undefined1 *)(lVar17 + 0x14) = 1;",
    "lVar17 = *param_1;",
    "local_a8 = (longlong *)0x0;",
    "uStack_a0 = 0;",
    "uStack_d0 = (undefined4)uStack_134;",
    "uStack_cc = uStack_134._4_4_;",
    "uStack_c8 = uStack_12c;",
    "local_b4 = uStack_118;",
    "local_98 = 0xffffffff;",
    "local_94 = 0;",
    "local_90 = 2;",
    "local_88 = 0;",
    "local_80 = 0;",
    "local_78 = 1;",
    "local_f0 = uVar15;",
    "uStack_ec = uVar20;",
    "local_e8 = uVar19;",
    "local_ac = uVar14 << 0x10 | uVar14 >> 0x10;",
    "plVar13 = (longlong *)FUN_140791190(0xe0,8);",
    "local_108 = plVar16;",
    "if (plVar13 != (longlong *)0x0) {\r\n        plVar2 = plVar13 + 4;",
    "*(undefined4 *)(plVar13 + 5) = 1;",
    "*(int *)((longlong)plVar13 + 0x2c) = iVar18;",
    "*(uint *)(plVar13 + 6) =\r\n             (((uint)bVar3 * 0x100 + (uint)bVar4) * 0x100 + (uint)bVar5) * 0x100 + (uint)bVar6;",
    "*(uint *)((longlong)plVar13 + 0x34) = (uint)(byte)-cVar7;",
    "*plVar2 = (longlong)&PTR_FUN_140b92ee8;",
    "*(undefined1 *)(plVar13 + 7) = 0;",
    "plVar13[8] = lVar17;",
    "FUN_140164280(plVar13 + 9,&local_f8);",
    "plVar13[0x1a] = CONCAT44(uStack_ec,local_f0);",
    "*(uint *)(plVar13 + 0x1b) = local_e8;",
    "*plVar13 = (longlong)&PTR_FUN_140b8dda8;",
    "*(undefined4 *)(plVar13 + 1) = 1;",
    "*(undefined4 *)((longlong)plVar13 + 0xc) = 1;",
    "plVar13[2] = 1;",
    "plVar13[3] = (longlong)plVar2;",
    "plVar16 = plVar13;",
    "local_108 = plVar2;",
    "}\r\n      local_110 = plVar16;",
    "FUN_14019a870(*(undefined8 *)(*param_1 + 0x198c0),&local_110,0);",
    "if (plVar16 != (longlong *)0x0) {\r\n        LOCK();",
    "plVar13 = plVar16 + 1;",
    "lVar17 = *plVar13;",
    "*(int *)plVar13 = (int)*plVar13 + -1;",
    "UNLOCK();",
    "if ((int)lVar17 == 1) {\r\n          (**(code **)(*plVar16 + 8))(plVar16);",
    "LOCK();",
    "piVar1 = (int *)((longlong)plVar16 + 0xc);",
    "iVar18 = *piVar1;",
    "*piVar1 = *piVar1 + -1;",
    "UNLOCK();",
    "if (iVar18 == 1) {\r\n            (**(code **)(*plVar16 + 0x10))(plVar16);",
    "}\r\n        }\r\n      }\r\n      plVar16 = local_a8;",
    "if (local_a8 != (longlong *)0x0) {\r\n        LOCK();",
    "plVar13 = local_a8 + 1;",
    "lVar17 = *plVar13;",
    "*(int *)plVar13 = (int)*plVar13 + -1;",
    "UNLOCK();",
    "if ((int)lVar17 == 1) {\r\n          (**(code **)(*local_a8 + 8))(local_a8);",
    "LOCK();",
    "piVar1 = (int *)((longlong)plVar16 + 0xc);",
    "iVar18 = *piVar1;",
    "*piVar1 = *piVar1 + -1;",
    "UNLOCK();",
    "if (iVar18 == 1) {\r\n            (**(code **)(*local_a8 + 0x10))();",
    "}\r\n        }\r\n      }\r\n      puVar12 = &DAT_140c9c250;",
    "}\r\n  }\r\n  return puVar12;",
    "}"
  ],
  "decompiledC": "\r\nundefined * FUN_1400fbf80(longlong *param_1,longlong param_2,undefined8 param_3,uint param_4)\r\n\r\n{\r\n  int *piVar1;\r\n  longlong *plVar2;\r\n  byte bVar3;\r\n  byte bVar4;\r\n  byte bVar5;\r\n  byte bVar6;\r\n  char cVar7;\r\n  longlong lVar8;\r\n  longlong lVar9;\r\n  byte bVar10;\r\n  byte bVar11;\r\n  undefined *puVar12;\r\n  longlong *plVar13;\r\n  uint uVar14;\r\n  uint uVar15;\r\n  longlong *plVar16;\r\n  longlong lVar17;\r\n  int iVar18;\r\n  uint uVar19;\r\n  uint uVar20;\r\n  undefined2 uStack_146;\r\n  uint uStack_144;\r\n  undefined4 uVar21;\r\n  uint uStack_13c;\r\n  undefined8 uStack_134;\r\n  undefined4 uStack_12c;\r\n  undefined4 uStack_128;\r\n  undefined4 local_124;\r\n  undefined4 uStack_120;\r\n  undefined4 uStack_11c;\r\n  undefined4 uStack_118;\r\n  longlong *local_110;\r\n  longlong *local_108;\r\n  undefined **local_f8;\r\n  uint local_f0;\r\n  uint uStack_ec;\r\n  uint local_e8;\r\n  ulonglong local_e4;\r\n  undefined8 uStack_dc;\r\n  undefined4 local_d4;\r\n  undefined4 uStack_d0;\r\n  undefined4 uStack_cc;\r\n  undefined4 uStack_c8;\r\n  undefined8 local_c4;\r\n  undefined8 uStack_bc;\r\n  undefined4 local_b4;\r\n  uint local_ac;\r\n  longlong *local_a8;\r\n  undefined8 uStack_a0;\r\n  undefined4 local_98;\r\n  undefined4 local_94;\r\n  undefined8 local_90;\r\n  undefined4 local_88;\r\n  undefined8 local_80;\r\n  undefined1 local_78;\r\n  undefined8 local_68;\r\n  undefined8 uStack_60;\r\n  undefined8 local_58;\r\n  undefined8 uStack_50;\r\n  undefined8 local_48;\r\n  undefined8 uStack_40;\r\n  \r\n  lVar8 = *(longlong *)(param_2 + 0x18);\r\n  lVar17 = lVar8 + 4;\r\n  plVar16 = (longlong *)0x0;\r\n  *(longlong *)(param_2 + 0x18) = lVar17;\r\n  lVar9 = *(longlong *)(param_2 + 0x10);\r\n  bVar3 = *(byte *)(lVar9 + -1 + lVar17);\r\n  bVar4 = *(byte *)(lVar9 + -2 + lVar17);\r\n  bVar5 = *(byte *)(lVar9 + -3 + lVar17);\r\n  bVar6 = *(byte *)(lVar9 + -4 + lVar17);\r\n  *(longlong *)(param_2 + 0x18) = lVar8 + 5;\r\n  cVar7 = *(char *)(lVar9 + lVar17);\r\n  lVar17 = lVar8 + 0xd;\r\n  *(longlong *)(param_2 + 0x18) = lVar17;\r\n  uVar14 = (((uint)*(byte *)(lVar9 + -2 + lVar17) * 0x100 + (uint)*(byte *)(lVar9 + -1 + lVar17)) *\r\n            0x100 + (uint)*(byte *)(lVar9 + -4 + lVar17)) * 0x100 +\r\n           (uint)*(byte *)(lVar9 + -3 + lVar17);\r\n  uVar15 = 0xffffffff;\r\n  uVar19 = 0;\r\n  if (uVar14 == 0xffffffff) {\r\n    uVar20 = 0;\r\n  }\r\n  else {\r\n    uVar19 = uVar14 & 0x3fff;\r\n    uVar20 = uVar14 >> 0xe & 0x3fff;\r\n    uVar15 = uVar14 >> 0x1c & 3;\r\n  }\r\n  *(longlong *)(param_2 + 0x18) = lVar8 + 0xe;\r\n  bVar10 = *(char *)(lVar9 + lVar17) + 0x80;\r\n  *(longlong *)(param_2 + 0x18) = lVar8 + 0x12;\r\n  uVar14 = *(uint *)(lVar9 + lVar8 + 0xe);\r\n  uVar14 = (uVar14 >> 8 ^ uVar14 << 8) & 0xff00ff ^ uVar14 << 8;\r\n  lVar17 = lVar8 + 0x1c;\r\n  *(longlong *)(param_2 + 0x18) = lVar17;\r\n  iVar18 = (uint)(byte)(*(char *)(lVar9 + -2 + lVar17) + 0x80) +\r\n           (uint)*(byte *)(lVar9 + -1 + lVar17) * 0x100;\r\n  *(longlong *)(param_2 + 0x18) = lVar8 + 0x20;\r\n  bVar11 = bVar10 >> 2 & 0x1f;\r\n  uStack_144 = 0;\r\n  uStack_13c = 0;\r\n  uStack_134 = 0;\r\n  uStack_12c = 0;\r\n  uStack_128 = 0;\r\n  local_124 = 0x3f800000;\r\n  uStack_120 = 0x3f800000;\r\n  uStack_11c = 0x3f800000;\r\n  uStack_118 = 0;\r\n  uVar21 = 0;\r\n  local_d4 = 0x3f800000;\r\n  if ((char)-((char)bVar10 >> 7) != '\\0') {\r\n    local_68 = 0;\r\n    uStack_60 = 0x3f80000000000000;\r\n    local_48 = 0;\r\n    uStack_40 = 0;\r\n    local_58 = 0;\r\n    uStack_50 = 0;\r\n    FUN_14010e3d0(&local_68,0,-((char)bVar10 >> 7),lVar9,bVar11,0,0x3f800000);\r\n    uStack_12c = (undefined4)uStack_50;\r\n    uStack_128 = uStack_50._4_4_;\r\n    local_124 = (undefined4)local_48;\r\n    uStack_120 = (undefined4)((ulonglong)local_48 >> 0x20);\r\n    uStack_11c = (undefined4)uStack_40;\r\n    uStack_118 = (undefined4)((ulonglong)uStack_40 >> 0x20);\r\n    uStack_144 = (uint)local_68 ^ 0x80000000;\r\n    uStack_13c = (uint)uStack_60 ^ 0x80000000;\r\n    param_4 = local_58._4_4_ ^ 0x80000000;\r\n    uStack_134 = local_58 ^ 0x8000000000000000;\r\n    uVar21 = local_68._4_4_;\r\n    local_d4 = uStack_60._4_4_;\r\n  }\r\n  if (*(longlong *)(*(longlong *)(*param_1 + 0x198c0) + 0x108) == 0) {\r\n    puVar12 = &DAT_140c9c270;\r\n  }\r\n  else {\r\n    lVar17 = FUN_1403370e0(*(longlong *)(*param_1 + 0x198c0) + 0x30,iVar18,0,param_4,bVar11,uVar21,\r\n                           local_d4);\r\n    if (*(longlong *)(lVar17 + 8) == 0) {\r\n      puVar12 = &DAT_140c9bb40;\r\n    }\r\n    else {\r\n      local_e4 = CONCAT44(uStack_144,CONCAT22(uStack_146,CONCAT11(bVar10,bVar11))) &\r\n                 0xffffffffffff03ff;\r\n      uStack_dc = CONCAT44(uStack_13c,uVar21);\r\n      lVar17 = *(longlong *)(*param_1 + 0x19888);\r\n      local_f8 = &PTR_FUN_140b8e038;\r\n      local_c4 = CONCAT44(local_124,uStack_128);\r\n      uStack_bc = CONCAT44(uStack_11c,uStack_120);\r\n      piVar1 = (int *)(lVar17 + 0x10);\r\n      *piVar1 = *piVar1 + 1;\r\n      *(undefined1 *)(lVar17 + 0x14) = 1;\r\n      lVar17 = *param_1;\r\n      local_a8 = (longlong *)0x0;\r\n      uStack_a0 = 0;\r\n      uStack_d0 = (undefined4)uStack_134;\r\n      uStack_cc = uStack_134._4_4_;\r\n      uStack_c8 = uStack_12c;\r\n      local_b4 = uStack_118;\r\n      local_98 = 0xffffffff;\r\n      local_94 = 0;\r\n      local_90 = 2;\r\n      local_88 = 0;\r\n      local_80 = 0;\r\n      local_78 = 1;\r\n      local_f0 = uVar15;\r\n      uStack_ec = uVar20;\r\n      local_e8 = uVar19;\r\n      local_ac = uVar14 << 0x10 | uVar14 >> 0x10;\r\n      plVar13 = (longlong *)FUN_140791190(0xe0,8);\r\n      local_108 = plVar16;\r\n      if (plVar13 != (longlong *)0x0) {\r\n        plVar2 = plVar13 + 4;\r\n        *(undefined4 *)(plVar13 + 5) = 1;\r\n        *(int *)((longlong)plVar13 + 0x2c) = iVar18;\r\n        *(uint *)(plVar13 + 6) =\r\n             (((uint)bVar3 * 0x100 + (uint)bVar4) * 0x100 + (uint)bVar5) * 0x100 + (uint)bVar6;\r\n        *(uint *)((longlong)plVar13 + 0x34) = (uint)(byte)-cVar7;\r\n        *plVar2 = (longlong)&PTR_FUN_140b92ee8;\r\n        *(undefined1 *)(plVar13 + 7) = 0;\r\n        plVar13[8] = lVar17;\r\n        FUN_140164280(plVar13 + 9,&local_f8);\r\n        plVar13[0x1a] = CONCAT44(uStack_ec,local_f0);\r\n        *(uint *)(plVar13 + 0x1b) = local_e8;\r\n        *plVar13 = (longlong)&PTR_FUN_140b8dda8;\r\n        *(undefined4 *)(plVar13 + 1) = 1;\r\n        *(undefined4 *)((longlong)plVar13 + 0xc) = 1;\r\n        plVar13[2] = 1;\r\n        plVar13[3] = (longlong)plVar2;\r\n        plVar16 = plVar13;\r\n        local_108 = plVar2;\r\n      }\r\n      local_110 = plVar16;\r\n      FUN_14019a870(*(undefined8 *)(*param_1 + 0x198c0),&local_110,0);\r\n      if (plVar16 != (longlong *)0x0) {\r\n        LOCK();\r\n        plVar13 = plVar16 + 1;\r\n        lVar17 = *plVar13;\r\n        *(int *)plVar13 = (int)*plVar13 + -1;\r\n        UNLOCK();\r\n        if ((int)lVar17 == 1) {\r\n          (**(code **)(*plVar16 + 8))(plVar16);\r\n          LOCK();\r\n          piVar1 = (int *)((longlong)plVar16 + 0xc);\r\n          iVar18 = *piVar1;\r\n          *piVar1 = *piVar1 + -1;\r\n          UNLOCK();\r\n          if (iVar18 == 1) {\r\n            (**(code **)(*plVar16 + 0x10))(plVar16);\r\n          }\r\n        }\r\n      }\r\n      plVar16 = local_a8;\r\n      if (local_a8 != (longlong *)0x0) {\r\n        LOCK();\r\n        plVar13 = local_a8 + 1;\r\n        lVar17 = *plVar13;\r\n        *(int *)plVar13 = (int)*plVar13 + -1;\r\n        UNLOCK();\r\n        if ((int)lVar17 == 1) {\r\n          (**(code **)(*local_a8 + 8))(local_a8);\r\n          LOCK();\r\n          piVar1 = (int *)((longlong)plVar16 + 0xc);\r\n          iVar18 = *piVar1;\r\n          *piVar1 = *piVar1 + -1;\r\n          UNLOCK();\r\n          if (iVar18 == 1) {\r\n            (**(code **)(*local_a8 + 0x10))();\r\n          }\r\n        }\r\n      }\r\n      puVar12 = &DAT_140c9c250;\r\n    }\r\n  }\r\n  return puVar12;\r\n}\r\n\r\n",
  "fields": [
    {
      "index": 0,
      "statementIndex": 66,
      "accessKind": "read",
      "width": 1,
      "rawType": "ubyte",
      "candidateType": "ubyte",
      "confidence": "strong",
      "source": "direct-scalar-load",
      "legacyType": "",
      "legacyAligned": false,
      "evidence": [
        "load-offset=25",
        "bVar3 = *(byte *)(lVar9 + -1 + lVar17);"
      ]
    },
    {
      "index": 1,
      "statementIndex": 66,
      "accessKind": "read",
      "width": 4,
      "rawType": "int",
      "candidateType": "intle",
      "confidence": "strong",
      "source": "decompiler-four-byte-expression",
      "legacyType": "",
      "legacyAligned": false,
      "evidence": [
        "offset-order=[25, 24, 23, 22]",
        "vars=[bVar3, bVar4, bVar5, bVar6]",
        "(((uint)bVar3 * 0x100 + (uint)bVar4) * 0x100 + (uint)bVar5) * 0x100 + (uint)bVar6"
      ]
    },
    {
      "index": 2,
      "statementIndex": 67,
      "accessKind": "read",
      "width": 1,
      "rawType": "ubyte",
      "candidateType": "ubyte",
      "confidence": "strong",
      "source": "direct-scalar-load",
      "legacyType": "",
      "legacyAligned": false,
      "evidence": [
        "load-offset=24",
        "bVar4 = *(byte *)(lVar9 + -2 + lVar17);"
      ]
    },
    {
      "index": 3,
      "statementIndex": 68,
      "accessKind": "read",
      "width": 1,
      "rawType": "ubyte",
      "candidateType": "ubyte",
      "confidence": "strong",
      "source": "direct-scalar-load",
      "legacyType": "",
      "legacyAligned": false,
      "evidence": [
        "load-offset=23",
        "bVar5 = *(byte *)(lVar9 + -3 + lVar17);"
      ]
    },
    {
      "index": 4,
      "statementIndex": 69,
      "accessKind": "read",
      "width": 1,
      "rawType": "ubyte",
      "candidateType": "ubyte",
      "confidence": "strong",
      "source": "direct-scalar-load",
      "legacyType": "",
      "legacyAligned": false,
      "evidence": [
        "load-offset=22",
        "bVar6 = *(byte *)(lVar9 + -4 + lVar17);"
      ]
    },
    {
      "index": 5,
      "statementIndex": 71,
      "accessKind": "read",
      "width": 1,
      "rawType": "ubyte",
      "candidateType": "ubyte",
      "confidence": "strong",
      "source": "direct-scalar-load",
      "legacyType": "",
      "legacyAligned": false,
      "evidence": [
        "load-offset=26",
        "cVar7 = *(char *)(lVar9 + lVar17);"
      ]
    },
    {
      "index": 6,
      "statementIndex": 74,
      "accessKind": "read",
      "width": 4,
      "rawType": "int",
      "candidateType": "intv1",
      "confidence": "strong",
      "source": "decompiler-byte-expression",
      "legacyType": "",
      "legacyAligned": false,
      "evidence": [
        "offset-order=[24, 25, 22, 23]",
        "uVar14 = (((uint)*(byte *)(lVar9 + -2 + lVar17) * 0x100 + (uint)*(byte *)(lVar9 + -1 + lVar17)) * 0x100 + (uint)*(byte *)(lVar9 + -4 + lVar17)) * 0x100 + (uint)*(byte *)(lVar9 + -3 + lVar17);"
      ]
    },
    {
      "index": 7,
      "statementIndex": 82,
      "accessKind": "read",
      "width": 1,
      "rawType": "ubyte",
      "candidateType": "ubyte",
      "confidence": "strong",
      "source": "direct-scalar-load",
      "legacyType": "",
      "legacyAligned": false,
      "evidence": [
        "load-offset=26",
        "bVar10 = *(char *)(lVar9 + lVar17) + 0x80;"
      ]
    },
    {
      "index": 8,
      "statementIndex": 84,
      "accessKind": "read",
      "width": 4,
      "rawType": "int",
      "candidateType": "intle",
      "confidence": "strong",
      "source": "direct-scalar-load",
      "legacyType": "",
      "legacyAligned": false,
      "evidence": [
        "load-offset=31",
        "uVar14 = *(uint *)(lVar9 + lVar8 + 0xe);"
      ]
    },
    {
      "index": 9,
      "statementIndex": 88,
      "accessKind": "read",
      "width": 2,
      "rawType": "ushort",
      "candidateType": "ushortle128",
      "confidence": "strong",
      "source": "decompiler-byte-expression",
      "legacyType": "",
      "legacyAligned": false,
      "evidence": [
        "offset-order=[24, 25]",
        "iVar18 = (uint)(byte)(*(char *)(lVar9 + -2 + lVar17) + 0x80) + (uint)*(byte *)(lVar9 + -1 + lVar17) * 0x100;",
        "transform=add"
      ]
    }
  ],
  "phase4TargetKind": "parser",
  "phase4QueuePriority": 100,
  "phase4QueueOpcode": 21,
  "phase4Side": "server"
}
